codeakscalc/__init__.py
codeakscalc-0.1.dist-info/LICENCE.txt
codeakscalc-0.1.dist-info/METADATA
codeakscalc-0.1.dist-info/WHEEL
codeakscalc-0.1.dist-info/top_level.txt
codeakscalc-0.1.dist-info/RECORD
