Metadata-Version: 2.1
Name: codeakscalc
Version: 0.1
Summary: Basic calculator
Author: Akshaya
Author-email: akshaya@gmail.com
Classifier: Programming Language :: Python :: 3
Classifier: License :: OSI Approved :: MIT License
Classifier: Operating System :: OS Independent
License-File: LICENCE.txt
